nonebot_plugin_comfyui-0.8.2.dist-info/METADATA
nonebot_plugin_comfyui-0.8.2.dist-info/WHEEL
nonebot_plugin_comfyui-0.8.2.dist-info/entry_points.txt
nonebot_plugin_comfyui/__init__.py
nonebot_plugin_comfyui/amusement/__init__.py
nonebot_plugin_comfyui/amusement/llm_tagger.py
nonebot_plugin_comfyui/amusement/search_danbooru.py
nonebot_plugin_comfyui/amusement/today_girl.py
nonebot_plugin_comfyui/backend/__init__.py
nonebot_plugin_comfyui/backend/comfyui.py
nonebot_plugin_comfyui/backend/help.py
nonebot_plugin_comfyui/backend/lora_utils.py
nonebot_plugin_comfyui/backend/pw.py
nonebot_plugin_comfyui/backend/update_check.py
nonebot_plugin_comfyui/backend/utils.py
nonebot_plugin_comfyui/backend/wd_audit.py
nonebot_plugin_comfyui/build_in_wf/controlnet以图绘图.json
nonebot_plugin_comfyui/build_in_wf/controlnet以图绘图_reflex.json
nonebot_plugin_comfyui/build_in_wf/img2img.json
nonebot_plugin_comfyui/build_in_wf/imgimg_reflex.json
nonebot_plugin_comfyui/build_in_wf/music_gen.json
nonebot_plugin_comfyui/build_in_wf/music_gen_reflex.json
nonebot_plugin_comfyui/build_in_wf/stale_audio.json
nonebot_plugin_comfyui/build_in_wf/stale_audio_reflex.json
nonebot_plugin_comfyui/build_in_wf/txt2img.json
nonebot_plugin_comfyui/build_in_wf/txt2img_reflex.json
nonebot_plugin_comfyui/build_in_wf/打标.json
nonebot_plugin_comfyui/build_in_wf/打标_reflex.json
nonebot_plugin_comfyui/build_in_wf/超分.json
nonebot_plugin_comfyui/build_in_wf/超分_reflex.json
nonebot_plugin_comfyui/build_in_wf/这里是内置工作流
nonebot_plugin_comfyui/command.py
nonebot_plugin_comfyui/config.py
nonebot_plugin_comfyui/exceptions.py
nonebot_plugin_comfyui/handler.py
nonebot_plugin_comfyui/parser.py
nonebot_plugin_comfyui/template/backend_status.html
nonebot_plugin_comfyui/template/config.yaml
nonebot_plugin_comfyui/template/example.md
nonebot_plugin_comfyui/template/help.html
nonebot_plugin_comfyui/template/row_template.html
nonebot_plugin_comfyui/template/show_wf_template.html
nonebot_plugin_comfyui-0.8.2.dist-info/RECORD
