Metadata-Version: 2.1
Name: nonebot-plugin-comfyui
Version: 0.8.2
Summary: 适用于NoneBot2的Comfyui绘图插件
Author-Email: DiaoDaiaChan <diaodaiachan@qq.com>
License: MIT
Requires-Python: >=3.10
Requires-Dist: aiohttp>=3.10.10
Requires-Dist: tqdm>=4.66.5
Requires-Dist: aiofiles>=24.1.0
Requires-Dist: nonebot_plugin_alconna>=0.53.1
Requires-Dist: pydantic>=1.10.0
Requires-Dist: nonebot2>=2.2.0
Requires-Dist: pillow>=11.0.0
Requires-Dist: nonebot-plugin-htmlrender>=0.2.0.3
Requires-Dist: filetype~=1.2.0
Requires-Dist: packaging~=24.2
Requires-Dist: Jinja2~=3.1.4
Requires-Dist: bs4~=0.0.2
Requires-Dist: ruamel.yaml~=0.18.6
Requires-Dist: qrcode~=8.0
Requires-Dist: baidu-translate-api~=1.0.0
